ubiops/__init__.py
ubiops/api_client.py
ubiops/configuration.py
ubiops/exceptions.py
ubiops/rest.py
ubiops/api/__init__.py
ubiops/api/blobs.py
ubiops/api/core_api.py
ubiops/api/deployment_requests.py
ubiops/api/deployments.py
ubiops/api/environments.py
ubiops/api/files.py
ubiops/api/imports_and_exports.py
ubiops/api/instances.py
ubiops/api/metrics.py
ubiops/api/organizations.py
ubiops/api/pipeline_requests.py
ubiops/api/pipelines.py
ubiops/api/projects.py
ubiops/api/request_schedules.py
ubiops/api/roles.py
ubiops/api/service_users.py
ubiops/api/status.py
ubiops/api/user.py
ubiops/api/webhooks.py
ubiops/models/__init__.py
ubiops/models/attachment_fields_list.py
ubiops/models/attachment_sources_list.py
ubiops/models/attachments_create.py
ubiops/models/attachments_list.py
ubiops/models/audit_list.py
ubiops/models/bucket_create.py
ubiops/models/bucket_detail.py
ubiops/models/bucket_list.py
ubiops/models/bucket_update.py
ubiops/models/build_list.py
ubiops/models/cluster.py
ubiops/models/deployment_create.py
ubiops/models/deployment_create_response.py
ubiops/models/deployment_detail.py
ubiops/models/deployment_input_field_create.py
ubiops/models/deployment_list.py
ubiops/models/deployment_output_field_create.py
ubiops/models/deployment_request_batch_create_response.py
ubiops/models/deployment_request_create_response.py
ubiops/models/deployment_request_detail.py
ubiops/models/deployment_request_list.py
ubiops/models/deployment_request_single_detail.py
ubiops/models/deployment_request_update.py
ubiops/models/deployment_update.py
ubiops/models/deployment_version_create.py
ubiops/models/deployment_version_detail.py
ubiops/models/deployment_version_list.py
ubiops/models/deployment_version_port.py
ubiops/models/deployment_version_update.py
ubiops/models/environment_build_dependency.py
ubiops/models/environment_build_list.py
ubiops/models/environment_build_update.py
ubiops/models/environment_create.py
ubiops/models/environment_detail.py
ubiops/models/environment_list.py
ubiops-4.11.0.dist-info/LICENSE
ubiops-4.11.0.dist-info/METADATA
ubiops-4.11.0.dist-info/WHEEL
ubiops-4.11.0.dist-info/top_level.txt
ubiops-4.11.0.dist-info/RECORD
