Metadata-Version: 2.1
Name: ubiops
Version: 4.11.0
Summary: UbiOps
Home-page: https://github.com/UbiOps/client-library-python.git
Author: UbiOps
License: Apache 2.0
Keywords: OpenAPI,OpenAPI-Generator,UbiOps
Platform: UNKNOWN
Requires-Dist: certifi>=14.05.14
Requires-Dist: python-dateutil>=2.5.3
Requires-Dist: pyyaml<7.0
Requires-Dist: requests<3.0,>=2.25.1
Requires-Dist: requests-toolbelt==1.0.0
Requires-Dist: schema==0.7.7
Requires-Dist: tqdm>=4.64.1
